MANIFEST.in
README.rst
setup.cfg
setup.py
c2c/__init__.py
c2c/versions.py
c2c.versions.egg-info/PKG-INFO
c2c.versions.egg-info/SOURCES.txt
c2c.versions.egg-info/dependency_links.txt
c2c.versions.egg-info/entry_points.txt
c2c.versions.egg-info/namespace_packages.txt
c2c.versions.egg-info/not-zip-safe
c2c.versions.egg-info/requires.txt
c2c.versions.egg-info/top_level.txt