Metadata-Version: 1.1
Name: c2c.versions
Version: 0.5dev2
Summary: Command to tests program version
Home-page: http://github.com/sbrunner/c2c.versions
Author: Stéphane Brunner
Author-email: stephane.brunner@camptocamp.com
License: BSD
Keywords: check package programme version
Platform: UNKNOWN
Classifier: Development Status :: 4 - Beta
Classifier: Environment :: Console
Classifier: Intended Audience :: Developers
Classifier: License :: OSI Approved :: BSD License
Classifier: Programming Language :: Python
Classifier: Programming Language :: Python :: 2.6
Classifier: Programming Language :: Python :: 2.7
Classifier: Programming Language :: Python :: 3.2
Classifier: Programming Language :: Python :: 3.3
Classifier: Programming Language :: Python :: 3.4
Classifier: Topic :: System :: Installation/Setup
